backend/=23.1
backend/README.md
backend/__init__.py
backend/api/__init__.py
backend/api/apps.py
backend/api/management/__init__.py
backend/api/management/commands/__init__.py
backend/api/management/commands/create_admin.py
backend/api/management/commands/wait_for_db.py
backend/api/middleware.py
backend/api/migrations/0001_initial.py
backend/api/migrations/0002_comment.py
backend/api/migrations/0002_project_single_class_classification.py
backend/api/migrations/0002_speech2text.py
backend/api/migrations/0003_merge_20200612_0205.py
backend/api/migrations/0004_merge_20210114_1117.py
backend/api/migrations/0005_auto_20210120_1730.py
backend/api/migrations/0005_auto_20210201_0603.py
backend/api/migrations/0006_merge_20210221_1258.py
backend/api/migrations/0007_auto_20210301_0302.py
backend/api/migrations/0008_auto_20210302_1013.py
backend/api/migrations/0009_annotations_relations_20210421_1445.py
backend/api/migrations/0009_auto_20210411_2330.py
backend/api/migrations/0009_tag.py
backend/api/migrations/0010_auto_20210413_0249.py
backend/api/migrations/0011_merge_0009_tag_0010_auto_20210413_0249.py
backend/api/migrations/0012_auto_20210514_0654.py
backend/api/migrations/0013_merge_20210528_1016.py
backend/api/migrations/0014_auto_20210603_0438.py
backend/api/migrations/0015_examplestate.py
backend/api/migrations/0016_auto_20211018_0556.py
backend/api/migrations/0017_example_uuid.py
backend/api/migrations/0018_alter_label_background_color.py
backend/api/migrations/0019_auto_20211124_0506.py
backend/api/migrations/0020_auto_20211221_1415.py
backend/api/migrations/0021_auto_20211221_1416.py
backend/api/migrations/0022_auto_20211221_1430.py
backend/api/migrations/0023_auto_20211221_1430.py
backend/api/migrations/0024_auto_20211221_1444.py
backend/api/migrations/0025_auto_20220107_0158.py
backend/api/migrations/0026_auto_20220107_0200.py
backend/api/migrations/0027_auto_20211222_0454.py
backend/api/migrations/0028_auto_20220111_0655.py
doccano_multi_label-1.8.4.2.dist-info/LICENSE
doccano_multi_label-1.8.4.2.dist-info/METADATA
doccano_multi_label-1.8.4.2.dist-info/WHEEL
doccano_multi_label-1.8.4.2.dist-info/entry_points.txt
doccano_multi_label-1.8.4.2.dist-info/RECORD
