Metadata-Version: 2.1
Name: doccano-multi-label
Version: 1.8.4.2
Summary: doccano, text annotation tool for machine learning practitioners
Home-page: https://doccano.github.io/doccano/
License: MIT
Author: Piyush
Author-email: piyush.balkishan@hotmail.com
Requires-Python: >=3.8,<4.0
Classifier: License :: OSI Approved :: MIT License
Classifier: Programming Language :: Python
Classifier: Programming Language :: Python :: 3
Classifier: Programming Language :: Python :: 3.8
Classifier: Programming Language :: Python :: 3.9
Classifier: Programming Language :: Python :: 3.10
Classifier: Programming Language :: Python :: 3.11
Classifier: Programming Language :: Python :: 3.12
Provides-Extra: mssql
Provides-Extra: postgresql
Requires-Dist: Django (>=4.1.7,<5.0.0)
Requires-Dist: SQLAlchemy (>=1.4.31,<2.0.0)
Requires-Dist: auto-labeling-pipeline (>=0.1.21,<0.2.0)
Requires-Dist: celery (>=5.2.3,<6.0.0)
Requires-Dist: chardet (>=4.0.0,<5.0.0)
Requires-Dist: dj-database-url (>=0.5.0,<0.6.0)
Requires-Dist: dj-rest-auth[with-social] (>=2.2.5,<3.0.0)
Requires-Dist: django-allauth (>=0.52.0,<0.53.0)
Requires-Dist: django-celery-results (==2.4.0)
Requires-Dist: django-cleanup (>=6.0.0,<7.0.0)
Requires-Dist: django-cors-headers (>=3.13.0,<4.0.0)
Requires-Dist: django-drf-filepond (>=0.5.0,<0.6.0)
Requires-Dist: django-filter (>=22.1,<23.0)
Requires-Dist: django-health-check (>=3.16.5,<4.0.0)
Requires-Dist: django-polymorphic (>=3.1.0,<4.0.0)
Requires-Dist: django-rest-polymorphic (>=0.1.9,<0.2.0)
Requires-Dist: django-storages[google] (>=1.13.1,<2.0.0)
Requires-Dist: djangorestframework (>=3.14.0,<4.0.0)
Requires-Dist: djangorestframework-xml (>=2.0.0,<3.0.0)
Requires-Dist: drf-yasg (>=1.21.5,<2.0.0)
Requires-Dist: environs (>=9.5.0,<10.0.0)
Requires-Dist: filetype (>=1.0.10,<2.0.0)
Requires-Dist: flower (>=1.2.0,<2.0.0)
Requires-Dist: furl (>=2.1.3,<3.0.0)
Requires-Dist: gunicorn (>=20.1.0,<21.0.0)
Requires-Dist: pandas (>=1.4.2,<2.0.0)
Requires-Dist: pydantic (>=2.0.3,<3.0.0)
Requires-Dist: pyexcel (>=0.7.0,<0.8.0)
Requires-Dist: pyexcel-xlsx (>=0.6.0,<0.7.0)
Requires-Dist: seqeval (>=1.2.2,<2.0.0)
Requires-Dist: waitress (>=2.0.0,<3.0.0)
Requires-Dist: whitenoise (>=6.0.0,<7.0.0)
Project-URL: Documentation, https://doccano.github.io/doccano/
Project-URL: Repository, https://github.com/doccano/doccano
